jinja2_django_version/__init__.py
jinja2_django_version/django_version.py
jinja2_django_version-1.1.2.dist-info/LICENSE
jinja2_django_version-1.1.2.dist-info/WHEEL
jinja2_django_version-1.1.2.dist-info/METADATA
jinja2_django_version-1.1.2.dist-info/RECORD
