Metadata-Version: 2.1
Name: jinja2-django-version
Version: 1.1.2
Summary: A Jinja2 extension that adds django version to templates.
Home-page: https://github.com/jmfederico/jinja2-django-version
License: BSD-3-Clause
Keywords: jinja2,extension,django,versions
Author: Federico Jaramillo Martínez
Author-email: federicojaramillom@gmail.com
Requires-Python: >=2.7, !=3.0.*, !=3.1.*, !=3.2.*, !=3.3.*
Classifier: Development Status :: 5 - Production/Stable
Classifier: Framework :: Django
Classifier: Intended Audience :: Developers
Classifier: License :: OSI Approved :: BSD License
Classifier: Natural Language :: English
Classifier: Programming Language :: Python :: 2
Classifier: Programming Language :: Python :: 2.7
Classifier: Programming Language :: Python :: 3
Classifier: Programming Language :: Python :: 3.4
Classifier: Programming Language :: Python :: 3.5
Classifier: Programming Language :: Python :: 3.6
Classifier: Programming Language :: Python :: 3.7
Requires-Dist: Jinja2 (>=2.0,<3.0)
Requires-Dist: django (>=1.11)
Project-URL: Repository, https://github.com/jmfederico/jinja2-django-version
